{"nodes": [{"id": "home_cbx_projects_autobiology_data_synonyms_json", "label": "synonyms.json", "file_type": "code", "source_file": "data/synonyms.json", "source_location": "L1"}, {"id": "data_synonyms_pbs_buffer", "label": "PBS buffer", "file_type": "code", "source_file": "data/synonyms.json", "source_location": "L2"}, {"id": "data_synonyms_pbs\u7f13\u51b2\u6db2", "label": "PBS\u7f13\u51b2\u6db2", "file_type": "code", "source_file": "data/synonyms.json", "source_location": "L4"}, {"id": "data_synonyms_pbs_\u7f13\u51b2\u6db2", "label": "PBS \u7f13\u51b2\u6db2", "file_type": "code", "source_file": "data/synonyms.json", "source_location": "L5"}, {"id": "data_synonyms_\u78f7\u9178\u76d0\u7f13\u51b2\u6db2", "label": "\u78f7\u9178\u76d0\u7f13\u51b2\u6db2", "file_type": "code", "source_file": "data/synonyms.json", "source_location": "L6"}, {"id": "data_synonyms_\u78f7\u9178\u76d0\u7f13\u51b2\u76d0\u6c34", "label": "\u78f7\u9178\u76d0\u7f13\u51b2\u76d0\u6c34", "file_type": "code", "source_file": "data/synonyms.json", "source_location": "L7"}, {"id": "data_synonyms_pbs", "label": "pbs", "file_type": "code", "source_file": "data/synonyms.json", "source_location": "L8"}, {"id": "data_synonyms_dpbs", "label": "dpbs", "file_type": "code", "source_file": "data/synonyms.json", "source_location": "L9"}, {"id": "data_synonyms_dpbs_buffer", "label": "DPBS buffer", "file_type": "code", "source_file": "data/synonyms.json", "source_location": "L10"}, {"id": "data_synonyms_hbss_buffer", "label": "HBSS buffer", "file_type": "code", "source_file": "data/synonyms.json", "source_location": "L11"}, {"id": "data_synonyms_dmem\u57f9\u517b\u57fa", "label": "DMEM\u57f9\u517b\u57fa", "file_type": "code", "source_file": "data/synonyms.json", "source_location": "L12"}, {"id": "data_synonyms_dmem_medium", "label": "DMEM medium", "file_type": "code", "source_file": "data/synonyms.json", "source_location": "L13"}, {"id": "data_synonyms_rpmi1640", "label": "RPMI1640", "file_type": "code", "source_file": "data/synonyms.json", "source_location": "L14"}, {"id": "data_synonyms_rpmi_1640", "label": "RPMI-1640", "file_type": "code", "source_file": "data/synonyms.json", "source_location": "L15"}, {"id": "data_synonyms_rpmi_1640_medium", "label": "RPMI 1640 medium", "file_type": "code", "source_file": "data/synonyms.json", "source_location": "L16"}, {"id": "data_synonyms_fbs", "label": "FBS", "file_type": "code", "source_file": "data/synonyms.json", "source_location": "L17"}, {"id": "data_synonyms_fetal_bovine_serum", "label": "fetal bovine serum", "file_type": "code", "source_file": "data/synonyms.json", "source_location": "L18"}, {"id": "data_synonyms_\u80ce\u725b\u8840\u6e05", "label": "\u80ce\u725b\u8840\u6e05", "file_type": "code", "source_file": "data/synonyms.json", "source_location": "L19"}, {"id": "data_synonyms_\u80f0\u9176", "label": "\u80f0\u9176", "file_type": "code", "source_file": "data/synonyms.json", "source_location": "L20"}, {"id": "data_synonyms_\u80f0\u86cb\u767d\u9176", "label": "\u80f0\u86cb\u767d\u9176", "file_type": "code", "source_file": "data/synonyms.json", "source_location": "L21"}, {"id": "data_synonyms_trypsin", "label": "trypsin", "file_type": "code", "source_file": "data/synonyms.json", "source_location": "L22"}, {"id": "data_synonyms_edta\u80f0\u9176", "label": "EDTA\u80f0\u9176", "file_type": "code", "source_file": "data/synonyms.json", "source_location": "L23"}, {"id": "data_synonyms_trypsin_edta", "label": "Trypsin EDTA", "file_type": "code", "source_file": "data/synonyms.json", "source_location": "L24"}, {"id": "data_synonyms_\u7ec6\u80de\u60ac\u6db2", "label": "\u7ec6\u80de\u60ac\u6db2", "file_type": "code", "source_file": "data/synonyms.json", "source_location": "L25"}, {"id": "data_synonyms_cell_suspension", "label": "cell suspension", "file_type": "code", "source_file": "data/synonyms.json", "source_location": "L26"}, {"id": "data_synonyms_\u7ec6\u80de\u6c89\u6dc0", "label": "\u7ec6\u80de\u6c89\u6dc0", "file_type": "code", "source_file": "data/synonyms.json", "source_location": "L27"}, {"id": "data_synonyms_cell_pellet", "label": "cell pellet", "file_type": "code", "source_file": "data/synonyms.json", "source_location": "L28"}, {"id": "data_synonyms_pellet", "label": "pellet", "file_type": "code", "source_file": "data/synonyms.json", "source_location": "L29"}, {"id": "data_synonyms_\u4e0a\u6e05", "label": "\u4e0a\u6e05", "file_type": "code", "source_file": "data/synonyms.json", "source_location": "L30"}, {"id": "data_synonyms_\u4e0a\u6e05\u6db2", "label": "\u4e0a\u6e05\u6db2", "file_type": "code", "source_file": "data/synonyms.json", "source_location": "L31"}, {"id": "data_synonyms_supernatant", "label": "supernatant", "file_type": "code", "source_file": "data/synonyms.json", "source_location": "L32"}, {"id": "data_synonyms_\u79bb\u5fc3\u74f6", "label": "\u79bb\u5fc3\u74f6", "file_type": "code", "source_file": "data/synonyms.json", "source_location": "L33"}, {"id": "data_synonyms_\u79bb\u5fc3\u7ba1", "label": "\u79bb\u5fc3\u7ba1", "file_type": "code", "source_file": "data/synonyms.json", "source_location": "L34"}, {"id": "data_synonyms_falcon\u7ba1", "label": "Falcon\u7ba1", "file_type": "code", "source_file": "data/synonyms.json", "source_location": "L35"}, {"id": "data_synonyms_falcon_tube", "label": "Falcon tube", "file_type": "code", "source_file": "data/synonyms.json", "source_location": "L36"}, {"id": "data_synonyms_conical_tube", "label": "conical tube", "file_type": "code", "source_file": "data/synonyms.json", "source_location": "L37"}, {"id": "data_synonyms_ep\u7ba1", "label": "EP\u7ba1", "file_type": "code", "source_file": "data/synonyms.json", "source_location": "L38"}, {"id": "data_synonyms_eppendorf\u7ba1", "label": "Eppendorf\u7ba1", "file_type": "code", "source_file": "data/synonyms.json", "source_location": "L39"}, {"id": "data_synonyms_microcentrifuge_tube", "label": "microcentrifuge tube", "file_type": "code", "source_file": "data/synonyms.json", "source_location": "L40"}, {"id": "data_synonyms_\u5b54\u677f", "label": "\u5b54\u677f", "file_type": "code", "source_file": "data/synonyms.json", "source_location": "L41"}, {"id": "data_synonyms_96\u5b54\u677f", "label": "96\u5b54\u677f", "file_type": "code", "source_file": "data/synonyms.json", "source_location": "L42"}, {"id": "data_synonyms_96_well_plate", "label": "96-well plate", "file_type": "code", "source_file": "data/synonyms.json", "source_location": "L43"}, {"id": "data_synonyms_24\u5b54\u677f", "label": "24\u5b54\u677f", "file_type": "code", "source_file": "data/synonyms.json", "source_location": "L44"}, {"id": "data_synonyms_24_well_plate", "label": "24-well plate", "file_type": "code", "source_file": "data/synonyms.json", "source_location": "L45"}, {"id": "data_synonyms_\u57f9\u517b\u74f6", "label": "\u57f9\u517b\u74f6", "file_type": "code", "source_file": "data/synonyms.json", "source_location": "L46"}, {"id": "data_synonyms_\u57f9\u517b\u5bb9\u5668", "label": "\u57f9\u517b\u5bb9\u5668", "file_type": "code", "source_file": "data/synonyms.json", "source_location": "L47"}, {"id": "data_synonyms_t25\u74f6", "label": "T25\u74f6", "file_type": "code", "source_file": "data/synonyms.json", "source_location": "L48"}, {"id": "data_synonyms_t75\u74f6", "label": "T75\u74f6", "file_type": "code", "source_file": "data/synonyms.json", "source_location": "L49"}, {"id": "data_synonyms_cell_culture_flask", "label": "cell culture flask", "file_type": "code", "source_file": "data/synonyms.json", "source_location": "L50"}, {"id": "data_synonyms_\u57f9\u517b\u76bf", "label": "\u57f9\u517b\u76bf", "file_type": "code", "source_file": "data/synonyms.json", "source_location": "L51"}, {"id": "data_synonyms_dish", "label": "dish", "file_type": "code", "source_file": "data/synonyms.json", "source_location": "L52"}, {"id": "data_synonyms_\u79fb\u6db2\u67aa", "label": "\u79fb\u6db2\u67aa", "file_type": "code", "source_file": "data/synonyms.json", "source_location": "L53"}, {"id": "data_synonyms_\u79fb\u6db2\u7ba1", "label": "\u79fb\u6db2\u7ba1", "file_type": "code", "source_file": "data/synonyms.json", "source_location": "L54"}, {"id": "data_synonyms_\u5438\u7ba1", "label": "\u5438\u7ba1", "file_type": "code", "source_file": "data/synonyms.json", "source_location": "L55"}, {"id": "data_synonyms_pipette", "label": "pipette", "file_type": "code", "source_file": "data/synonyms.json", "source_location": "L56"}, {"id": "data_synonyms_pipettor", "label": "pipettor", "file_type": "code", "source_file": "data/synonyms.json", "source_location": "L57"}, {"id": "data_synonyms_\u67aa\u5934", "label": "\u67aa\u5934", "file_type": "code", "source_file": "data/synonyms.json", "source_location": "L58"}, {"id": "data_synonyms_tip", "label": "tip", "file_type": "code", "source_file": "data/synonyms.json", "source_location": "L59"}, {"id": "data_synonyms_pipette_tip", "label": "pipette tip", "file_type": "code", "source_file": "data/synonyms.json", "source_location": "L60"}, {"id": "data_synonyms_\u8d85\u51c0\u53f0", "label": "\u8d85\u51c0\u53f0", "file_type": "code", "source_file": "data/synonyms.json", "source_location": "L61"}, {"id": "data_synonyms_\u5b89\u5168\u67dc", "label": "\u5b89\u5168\u67dc", "file_type": "code", "source_file": "data/synonyms.json", "source_location": "L62"}, {"id": "data_synonyms_\u751f\u7269\u5b89\u5168\u67dc", "label": "\u751f\u7269\u5b89\u5168\u67dc", "file_type": "code", "source_file": "data/synonyms.json", "source_location": "L63"}, {"id": "data_synonyms_bsc", "label": "BSC", "file_type": "code", "source_file": "data/synonyms.json", "source_location": "L64"}, {"id": "data_synonyms_biosafety_cabinet", "label": "biosafety cabinet", "file_type": "code", "source_file": "data/synonyms.json", "source_location": "L65"}, {"id": "data_synonyms_clean_bench", "label": "clean bench", "file_type": "code", "source_file": "data/synonyms.json", "source_location": "L66"}, {"id": "data_synonyms_\u57f9\u517b\u7bb1", "label": "\u57f9\u517b\u7bb1", "file_type": "code", "source_file": "data/synonyms.json", "source_location": "L67"}, {"id": "data_synonyms_\u7ec6\u80de\u57f9\u517b\u7bb1", "label": "\u7ec6\u80de\u57f9\u517b\u7bb1", "file_type": "code", "source_file": "data/synonyms.json", "source_location": "L68"}, {"id": "data_synonyms_co2_incubator", "label": "CO2 incubator", "file_type": "code", "source_file": "data/synonyms.json", "source_location": "L69"}, {"id": "data_synonyms_\u4e8c\u6c27\u5316\u78b3\u57f9\u517b\u7bb1", "label": "\u4e8c\u6c27\u5316\u78b3\u57f9\u517b\u7bb1", "file_type": "code", "source_file": "data/synonyms.json", "source_location": "L70"}, {"id": "data_synonyms_\u51b7\u51bb\u79bb\u5fc3\u673a", "label": "\u51b7\u51bb\u79bb\u5fc3\u673a", "file_type": "code", "source_file": "data/synonyms.json", "source_location": "L71"}, {"id": "data_synonyms_refrigerated_centrifuge", "label": "refrigerated centrifuge", "file_type": "code", "source_file": "data/synonyms.json", "source_location": "L72"}, {"id": "data_synonyms_\u79bb\u5fc3\u673a", "label": "\u79bb\u5fc3\u673a", "file_type": "code", "source_file": "data/synonyms.json", "source_location": "L73"}, {"id": "data_synonyms_centrifuge", "label": "centrifuge", "file_type": "code", "source_file": "data/synonyms.json", "source_location": "L74"}, {"id": "data_synonyms_\u8f6c\u5b50", "label": "\u8f6c\u5b50", "file_type": "code", "source_file": "data/synonyms.json", "source_location": "L75"}, {"id": "data_synonyms_rotor", "label": "rotor", "file_type": "code", "source_file": "data/synonyms.json", "source_location": "L76"}, {"id": "data_synonyms_\u51b0\u4e0a", "label": "\u51b0\u4e0a", "file_type": "code", "source_file": "data/synonyms.json", "source_location": "L77"}, {"id": "data_synonyms_on_ice", "label": "on ice", "file_type": "code", "source_file": "data/synonyms.json", "source_location": "L78"}, {"id": "data_synonyms_4\u6444\u6c0f\u5ea6", "label": "4\u6444\u6c0f\u5ea6", "file_type": "code", "source_file": "data/synonyms.json", "source_location": "L79"}, {"id": "data_synonyms_4_c", "label": "4 \u00b0C", "file_type": "code", "source_file": "data/synonyms.json", "source_location": "L80"}, {"id": "data_synonyms_37\u6444\u6c0f\u5ea6", "label": "37\u6444\u6c0f\u5ea6", "file_type": "code", "source_file": "data/synonyms.json", "source_location": "L81"}, {"id": "data_synonyms_37_c", "label": "37 \u00b0C", "file_type": "code", "source_file": "data/synonyms.json", "source_location": "L82"}, {"id": "data_synonyms_\u5ba4\u6e29", "label": "\u5ba4\u6e29", "file_type": "code", "source_file": "data/synonyms.json", "source_location": "L83"}, {"id": "data_synonyms_rt", "label": "RT", "file_type": "code", "source_file": "data/synonyms.json", "source_location": "L84"}, {"id": "data_synonyms_room_temperature", "label": "room temperature", "file_type": "code", "source_file": "data/synonyms.json", "source_location": "L85"}, {"id": "data_synonyms_\u65e0\u83cc", "label": "\u65e0\u83cc", "file_type": "code", "source_file": "data/synonyms.json", "source_location": "L86"}, {"id": "data_synonyms_sterile", "label": "sterile", "file_type": "code", "source_file": "data/synonyms.json", "source_location": "L87"}, {"id": "data_synonyms_\u907f\u5149", "label": "\u907f\u5149", "file_type": "code", "source_file": "data/synonyms.json", "source_location": "L88"}, {"id": "data_synonyms_dark_condition", "label": "dark condition", "file_type": "code", "source_file": "data/synonyms.json", "source_location": "L89"}, {"id": "data_synonyms_co2", "label": "CO2", "file_type": "code", "source_file": "data/synonyms.json", "source_location": "L90"}, {"id": "data_synonyms_\u4e8c\u6c27\u5316\u78b3", "label": "\u4e8c\u6c27\u5316\u78b3", "file_type": "code", "source_file": "data/synonyms.json", "source_location": "L92"}], "edges": [{"source": "home_cbx_projects_autobiology_data_synonyms_json", "target": "data_synonyms_pbs_buffer", "relation": "contains", "confidence": "EXTRACTED", "source_file": "data/synonyms.json", "source_location": "L2", "weight": 1.0}, {"source": "home_cbx_projects_autobiology_data_synonyms_json", "target": "data_synonyms_pbs_buffer", "relation": "contains", "confidence": "EXTRACTED", "source_file": "data/synonyms.json", "source_location": "L3", "weight": 1.0}, {"source": "home_cbx_projects_autobiology_data_synonyms_json", "target": "data_synonyms_pbs\u7f13\u51b2\u6db2", "relation": "contains", "confidence": "EXTRACTED", "source_file": "data/synonyms.json", "source_location": "L4", "weight": 1.0}, {"source": "home_cbx_projects_autobiology_data_synonyms_json", "target": "data_synonyms_pbs_\u7f13\u51b2\u6db2", "relation": "contains", "confidence": "EXTRACTED", "source_file": "data/synonyms.json", "source_location": "L5", "weight": 1.0}, {"source": "home_cbx_projects_autobiology_data_synonyms_json", "target": "data_synonyms_\u78f7\u9178\u76d0\u7f13\u51b2\u6db2", "relation": "contains", "confidence": "EXTRACTED", "source_file": "data/synonyms.json", "source_location": "L6", "weight": 1.0}, {"source": "home_cbx_projects_autobiology_data_synonyms_json", "target": "data_synonyms_\u78f7\u9178\u76d0\u7f13\u51b2\u76d0\u6c34", "relation": "contains", "confidence": "EXTRACTED", "source_file": "data/synonyms.json", "source_location": "L7", "weight": 1.0}, {"source": "home_cbx_projects_autobiology_data_synonyms_json", "target": "data_synonyms_pbs", "relation": "contains", "confidence": "EXTRACTED", "source_file": "data/synonyms.json", "source_location": "L8", "weight": 1.0}, {"source": "home_cbx_projects_autobiology_data_synonyms_json", "target": "data_synonyms_dpbs", "relation": "contains", "confidence": "EXTRACTED", "source_file": "data/synonyms.json", "source_location": "L9", "weight": 1.0}, {"source": "home_cbx_projects_autobiology_data_synonyms_json", "target": "data_synonyms_dpbs_buffer", "relation": "contains", "confidence": "EXTRACTED", "source_file": "data/synonyms.json", "source_location": "L10", "weight": 1.0}, {"source": "home_cbx_projects_autobiology_data_synonyms_json", "target": "data_synonyms_hbss_buffer", "relation": "contains", "confidence": "EXTRACTED", "source_file": "data/synonyms.json", "source_location": "L11", "weight": 1.0}, {"source": "home_cbx_projects_autobiology_data_synonyms_json", "target": "data_synonyms_dmem\u57f9\u517b\u57fa", "relation": "contains", "confidence": "EXTRACTED", "source_file": "data/synonyms.json", "source_location": "L12", "weight": 1.0}, {"source": "home_cbx_projects_autobiology_data_synonyms_json", "target": "data_synonyms_dmem_medium", "relation": "contains", "confidence": "EXTRACTED", "source_file": "data/synonyms.json", "source_location": "L13", "weight": 1.0}, {"source": "home_cbx_projects_autobiology_data_synonyms_json", "target": "data_synonyms_rpmi1640", "relation": "contains", "confidence": "EXTRACTED", "source_file": "data/synonyms.json", "source_location": "L14", "weight": 1.0}, {"source": "home_cbx_projects_autobiology_data_synonyms_json", "target": "data_synonyms_rpmi_1640", "relation": "contains", "confidence": "EXTRACTED", "source_file": "data/synonyms.json", "source_location": "L15", "weight": 1.0}, {"source": "home_cbx_projects_autobiology_data_synonyms_json", "target": "data_synonyms_rpmi_1640_medium", "relation": "contains", "confidence": "EXTRACTED", "source_file": "data/synonyms.json", "source_location": "L16", "weight": 1.0}, {"source": "home_cbx_projects_autobiology_data_synonyms_json", "target": "data_synonyms_fbs", "relation": "contains", "confidence": "EXTRACTED", "source_file": "data/synonyms.json", "source_location": "L17", "weight": 1.0}, {"source": "home_cbx_projects_autobiology_data_synonyms_json", "target": "data_synonyms_fetal_bovine_serum", "relation": "contains", "confidence": "EXTRACTED", "source_file": "data/synonyms.json", "source_location": "L18", "weight": 1.0}, {"source": "home_cbx_projects_autobiology_data_synonyms_json", "target": "data_synonyms_\u80ce\u725b\u8840\u6e05", "relation": "contains", "confidence": "EXTRACTED", "source_file": "data/synonyms.json", "source_location": "L19", "weight": 1.0}, {"source": "home_cbx_projects_autobiology_data_synonyms_json", "target": "data_synonyms_\u80f0\u9176", "relation": "contains", "confidence": "EXTRACTED", "source_file": "data/synonyms.json", "source_location": "L20", "weight": 1.0}, {"source": "home_cbx_projects_autobiology_data_synonyms_json", "target": "data_synonyms_\u80f0\u86cb\u767d\u9176", "relation": "contains", "confidence": "EXTRACTED", "source_file": "data/synonyms.json", "source_location": "L21", "weight": 1.0}, {"source": "home_cbx_projects_autobiology_data_synonyms_json", "target": "data_synonyms_trypsin", "relation": "contains", "confidence": "EXTRACTED", "source_file": "data/synonyms.json", "source_location": "L22", "weight": 1.0}, {"source": "home_cbx_projects_autobiology_data_synonyms_json", "target": "data_synonyms_edta\u80f0\u9176", "relation": "contains", "confidence": "EXTRACTED", "source_file": "data/synonyms.json", "source_location": "L23", "weight": 1.0}, {"source": "home_cbx_projects_autobiology_data_synonyms_json", "target": "data_synonyms_trypsin_edta", "relation": "contains", "confidence": "EXTRACTED", "source_file": "data/synonyms.json", "source_location": "L24", "weight": 1.0}, {"source": "home_cbx_projects_autobiology_data_synonyms_json", "target": "data_synonyms_\u7ec6\u80de\u60ac\u6db2", "relation": "contains", "confidence": "EXTRACTED", "source_file": "data/synonyms.json", "source_location": "L25", "weight": 1.0}, {"source": "home_cbx_projects_autobiology_data_synonyms_json", "target": "data_synonyms_cell_suspension", "relation": "contains", "confidence": "EXTRACTED", "source_file": "data/synonyms.json", "source_location": "L26", "weight": 1.0}, {"source": "home_cbx_projects_autobiology_data_synonyms_json", "target": "data_synonyms_\u7ec6\u80de\u6c89\u6dc0", "relation": "contains", "confidence": "EXTRACTED", "source_file": "data/synonyms.json", "source_location": "L27", "weight": 1.0}, {"source": "home_cbx_projects_autobiology_data_synonyms_json", "target": "data_synonyms_cell_pellet", "relation": "contains", "confidence": "EXTRACTED", "source_file": "data/synonyms.json", "source_location": "L28", "weight": 1.0}, {"source": "home_cbx_projects_autobiology_data_synonyms_json", "target": "data_synonyms_pellet", "relation": "contains", "confidence": "EXTRACTED", "source_file": "data/synonyms.json", "source_location": "L29", "weight": 1.0}, {"source": "home_cbx_projects_autobiology_data_synonyms_json", "target": "data_synonyms_\u4e0a\u6e05", "relation": "contains", "confidence": "EXTRACTED", "source_file": "data/synonyms.json", "source_location": "L30", "weight": 1.0}, {"source": "home_cbx_projects_autobiology_data_synonyms_json", "target": "data_synonyms_\u4e0a\u6e05\u6db2", "relation": "contains", "confidence": "EXTRACTED", "source_file": "data/synonyms.json", "source_location": "L31", "weight": 1.0}, {"source": "home_cbx_projects_autobiology_data_synonyms_json", "target": "data_synonyms_supernatant", "relation": "contains", "confidence": "EXTRACTED", "source_file": "data/synonyms.json", "source_location": "L32", "weight": 1.0}, {"source": "home_cbx_projects_autobiology_data_synonyms_json", "target": "data_synonyms_\u79bb\u5fc3\u74f6", "relation": "contains", "confidence": "EXTRACTED", "source_file": "data/synonyms.json", "source_location": "L33", "weight": 1.0}, {"source": "home_cbx_projects_autobiology_data_synonyms_json", "target": "data_synonyms_\u79bb\u5fc3\u7ba1", "relation": "contains", "confidence": "EXTRACTED", "source_file": "data/synonyms.json", "source_location": "L34", "weight": 1.0}, {"source": "home_cbx_projects_autobiology_data_synonyms_json", "target": "data_synonyms_falcon\u7ba1", "relation": "contains", "confidence": "EXTRACTED", "source_file": "data/synonyms.json", "source_location": "L35", "weight": 1.0}, {"source": "home_cbx_projects_autobiology_data_synonyms_json", "target": "data_synonyms_falcon_tube", "relation": "contains", "confidence": "EXTRACTED", "source_file": "data/synonyms.json", "source_location": "L36", "weight": 1.0}, {"source": "home_cbx_projects_autobiology_data_synonyms_json", "target": "data_synonyms_conical_tube", "relation": "contains", "confidence": "EXTRACTED", "source_file": "data/synonyms.json", "source_location": "L37", "weight": 1.0}, {"source": "home_cbx_projects_autobiology_data_synonyms_json", "target": "data_synonyms_ep\u7ba1", "relation": "contains", "confidence": "EXTRACTED", "source_file": "data/synonyms.json", "source_location": "L38", "weight": 1.0}, {"source": "home_cbx_projects_autobiology_data_synonyms_json", "target": "data_synonyms_eppendorf\u7ba1", "relation": "contains", "confidence": "EXTRACTED", "source_file": "data/synonyms.json", "source_location": "L39", "weight": 1.0}, {"source": "home_cbx_projects_autobiology_data_synonyms_json", "target": "data_synonyms_microcentrifuge_tube", "relation": "contains", "confidence": "EXTRACTED", "source_file": "data/synonyms.json", "source_location": "L40", "weight": 1.0}, {"source": "home_cbx_projects_autobiology_data_synonyms_json", "target": "data_synonyms_\u5b54\u677f", "relation": "contains", "confidence": "EXTRACTED", "source_file": "data/synonyms.json", "source_location": "L41", "weight": 1.0}, {"source": "home_cbx_projects_autobiology_data_synonyms_json", "target": "data_synonyms_96\u5b54\u677f", "relation": "contains", "confidence": "EXTRACTED", "source_file": "data/synonyms.json", "source_location": "L42", "weight": 1.0}, {"source": "home_cbx_projects_autobiology_data_synonyms_json", "target": "data_synonyms_96_well_plate", "relation": "contains", "confidence": "EXTRACTED", "source_file": "data/synonyms.json", "source_location": "L43", "weight": 1.0}, {"source": "home_cbx_projects_autobiology_data_synonyms_json", "target": "data_synonyms_24\u5b54\u677f", "relation": "contains", "confidence": "EXTRACTED", "source_file": "data/synonyms.json", "source_location": "L44", "weight": 1.0}, {"source": "home_cbx_projects_autobiology_data_synonyms_json", "target": "data_synonyms_24_well_plate", "relation": "contains", "confidence": "EXTRACTED", "source_file": "data/synonyms.json", "source_location": "L45", "weight": 1.0}, {"source": "home_cbx_projects_autobiology_data_synonyms_json", "target": "data_synonyms_\u57f9\u517b\u74f6", "relation": "contains", "confidence": "EXTRACTED", "source_file": "data/synonyms.json", "source_location": "L46", "weight": 1.0}, {"source": "home_cbx_projects_autobiology_data_synonyms_json", "target": "data_synonyms_\u57f9\u517b\u5bb9\u5668", "relation": "contains", "confidence": "EXTRACTED", "source_file": "data/synonyms.json", "source_location": "L47", "weight": 1.0}, {"source": "home_cbx_projects_autobiology_data_synonyms_json", "target": "data_synonyms_t25\u74f6", "relation": "contains", "confidence": "EXTRACTED", "source_file": "data/synonyms.json", "source_location": "L48", "weight": 1.0}, {"source": "home_cbx_projects_autobiology_data_synonyms_json", "target": "data_synonyms_t75\u74f6", "relation": "contains", "confidence": "EXTRACTED", "source_file": "data/synonyms.json", "source_location": "L49", "weight": 1.0}, {"source": "home_cbx_projects_autobiology_data_synonyms_json", "target": "data_synonyms_cell_culture_flask", "relation": "contains", "confidence": "EXTRACTED", "source_file": "data/synonyms.json", "source_location": "L50", "weight": 1.0}, {"source": "home_cbx_projects_autobiology_data_synonyms_json", "target": "data_synonyms_\u57f9\u517b\u76bf", "relation": "contains", "confidence": "EXTRACTED", "source_file": "data/synonyms.json", "source_location": "L51", "weight": 1.0}, {"source": "home_cbx_projects_autobiology_data_synonyms_json", "target": "data_synonyms_dish", "relation": "contains", "confidence": "EXTRACTED", "source_file": "data/synonyms.json", "source_location": "L52", "weight": 1.0}, {"source": "home_cbx_projects_autobiology_data_synonyms_json", "target": "data_synonyms_\u79fb\u6db2\u67aa", "relation": "contains", "confidence": "EXTRACTED", "source_file": "data/synonyms.json", "source_location": "L53", "weight": 1.0}, {"source": "home_cbx_projects_autobiology_data_synonyms_json", "target": "data_synonyms_\u79fb\u6db2\u7ba1", "relation": "contains", "confidence": "EXTRACTED", "source_file": "data/synonyms.json", "source_location": "L54", "weight": 1.0}, {"source": "home_cbx_projects_autobiology_data_synonyms_json", "target": "data_synonyms_\u5438\u7ba1", "relation": "contains", "confidence": "EXTRACTED", "source_file": "data/synonyms.json", "source_location": "L55", "weight": 1.0}, {"source": "home_cbx_projects_autobiology_data_synonyms_json", "target": "data_synonyms_pipette", "relation": "contains", "confidence": "EXTRACTED", "source_file": "data/synonyms.json", "source_location": "L56", "weight": 1.0}, {"source": "home_cbx_projects_autobiology_data_synonyms_json", "target": "data_synonyms_pipettor", "relation": "contains", "confidence": "EXTRACTED", "source_file": "data/synonyms.json", "source_location": "L57", "weight": 1.0}, {"source": "home_cbx_projects_autobiology_data_synonyms_json", "target": "data_synonyms_\u67aa\u5934", "relation": "contains", "confidence": "EXTRACTED", "source_file": "data/synonyms.json", "source_location": "L58", "weight": 1.0}, {"source": "home_cbx_projects_autobiology_data_synonyms_json", "target": "data_synonyms_tip", "relation": "contains", "confidence": "EXTRACTED", "source_file": "data/synonyms.json", "source_location": "L59", "weight": 1.0}, {"source": "home_cbx_projects_autobiology_data_synonyms_json", "target": "data_synonyms_pipette_tip", "relation": "contains", "confidence": "EXTRACTED", "source_file": "data/synonyms.json", "source_location": "L60", "weight": 1.0}, {"source": "home_cbx_projects_autobiology_data_synonyms_json", "target": "data_synonyms_\u8d85\u51c0\u53f0", "relation": "contains", "confidence": "EXTRACTED", "source_file": "data/synonyms.json", "source_location": "L61", "weight": 1.0}, {"source": "home_cbx_projects_autobiology_data_synonyms_json", "target": "data_synonyms_\u5b89\u5168\u67dc", "relation": "contains", "confidence": "EXTRACTED", "source_file": "data/synonyms.json", "source_location": "L62", "weight": 1.0}, {"source": "home_cbx_projects_autobiology_data_synonyms_json", "target": "data_synonyms_\u751f\u7269\u5b89\u5168\u67dc", "relation": "contains", "confidence": "EXTRACTED", "source_file": "data/synonyms.json", "source_location": "L63", "weight": 1.0}, {"source": "home_cbx_projects_autobiology_data_synonyms_json", "target": "data_synonyms_bsc", "relation": "contains", "confidence": "EXTRACTED", "source_file": "data/synonyms.json", "source_location": "L64", "weight": 1.0}, {"source": "home_cbx_projects_autobiology_data_synonyms_json", "target": "data_synonyms_biosafety_cabinet", "relation": "contains", "confidence": "EXTRACTED", "source_file": "data/synonyms.json", "source_location": "L65", "weight": 1.0}, {"source": "home_cbx_projects_autobiology_data_synonyms_json", "target": "data_synonyms_clean_bench", "relation": "contains", "confidence": "EXTRACTED", "source_file": "data/synonyms.json", "source_location": "L66", "weight": 1.0}, {"source": "home_cbx_projects_autobiology_data_synonyms_json", "target": "data_synonyms_\u57f9\u517b\u7bb1", "relation": "contains", "confidence": "EXTRACTED", "source_file": "data/synonyms.json", "source_location": "L67", "weight": 1.0}, {"source": "home_cbx_projects_autobiology_data_synonyms_json", "target": "data_synonyms_\u7ec6\u80de\u57f9\u517b\u7bb1", "relation": "contains", "confidence": "EXTRACTED", "source_file": "data/synonyms.json", "source_location": "L68", "weight": 1.0}, {"source": "home_cbx_projects_autobiology_data_synonyms_json", "target": "data_synonyms_co2_incubator", "relation": "contains", "confidence": "EXTRACTED", "source_file": "data/synonyms.json", "source_location": "L69", "weight": 1.0}, {"source": "home_cbx_projects_autobiology_data_synonyms_json", "target": "data_synonyms_\u4e8c\u6c27\u5316\u78b3\u57f9\u517b\u7bb1", "relation": "contains", "confidence": "EXTRACTED", "source_file": "data/synonyms.json", "source_location": "L70", "weight": 1.0}, {"source": "home_cbx_projects_autobiology_data_synonyms_json", "target": "data_synonyms_\u51b7\u51bb\u79bb\u5fc3\u673a", "relation": "contains", "confidence": "EXTRACTED", "source_file": "data/synonyms.json", "source_location": "L71", "weight": 1.0}, {"source": "home_cbx_projects_autobiology_data_synonyms_json", "target": "data_synonyms_refrigerated_centrifuge", "relation": "contains", "confidence": "EXTRACTED", "source_file": "data/synonyms.json", "source_location": "L72", "weight": 1.0}, {"source": "home_cbx_projects_autobiology_data_synonyms_json", "target": "data_synonyms_\u79bb\u5fc3\u673a", "relation": "contains", "confidence": "EXTRACTED", "source_file": "data/synonyms.json", "source_location": "L73", "weight": 1.0}, {"source": "home_cbx_projects_autobiology_data_synonyms_json", "target": "data_synonyms_centrifuge", "relation": "contains", "confidence": "EXTRACTED", "source_file": "data/synonyms.json", "source_location": "L74", "weight": 1.0}, {"source": "home_cbx_projects_autobiology_data_synonyms_json", "target": "data_synonyms_\u8f6c\u5b50", "relation": "contains", "confidence": "EXTRACTED", "source_file": "data/synonyms.json", "source_location": "L75", "weight": 1.0}, {"source": "home_cbx_projects_autobiology_data_synonyms_json", "target": "data_synonyms_rotor", "relation": "contains", "confidence": "EXTRACTED", "source_file": "data/synonyms.json", "source_location": "L76", "weight": 1.0}, {"source": "home_cbx_projects_autobiology_data_synonyms_json", "target": "data_synonyms_\u51b0\u4e0a", "relation": "contains", "confidence": "EXTRACTED", "source_file": "data/synonyms.json", "source_location": "L77", "weight": 1.0}, {"source": "home_cbx_projects_autobiology_data_synonyms_json", "target": "data_synonyms_on_ice", "relation": "contains", "confidence": "EXTRACTED", "source_file": "data/synonyms.json", "source_location": "L78", "weight": 1.0}, {"source": "home_cbx_projects_autobiology_data_synonyms_json", "target": "data_synonyms_4\u6444\u6c0f\u5ea6", "relation": "contains", "confidence": "EXTRACTED", "source_file": "data/synonyms.json", "source_location": "L79", "weight": 1.0}, {"source": "home_cbx_projects_autobiology_data_synonyms_json", "target": "data_synonyms_4_c", "relation": "contains", "confidence": "EXTRACTED", "source_file": "data/synonyms.json", "source_location": "L80", "weight": 1.0}, {"source": "home_cbx_projects_autobiology_data_synonyms_json", "target": "data_synonyms_37\u6444\u6c0f\u5ea6", "relation": "contains", "confidence": "EXTRACTED", "source_file": "data/synonyms.json", "source_location": "L81", "weight": 1.0}, {"source": "home_cbx_projects_autobiology_data_synonyms_json", "target": "data_synonyms_37_c", "relation": "contains", "confidence": "EXTRACTED", "source_file": "data/synonyms.json", "source_location": "L82", "weight": 1.0}, {"source": "home_cbx_projects_autobiology_data_synonyms_json", "target": "data_synonyms_\u5ba4\u6e29", "relation": "contains", "confidence": "EXTRACTED", "source_file": "data/synonyms.json", "source_location": "L83", "weight": 1.0}, {"source": "home_cbx_projects_autobiology_data_synonyms_json", "target": "data_synonyms_rt", "relation": "contains", "confidence": "EXTRACTED", "source_file": "data/synonyms.json", "source_location": "L84", "weight": 1.0}, {"source": "home_cbx_projects_autobiology_data_synonyms_json", "target": "data_synonyms_room_temperature", "relation": "contains", "confidence": "EXTRACTED", "source_file": "data/synonyms.json", "source_location": "L85", "weight": 1.0}, {"source": "home_cbx_projects_autobiology_data_synonyms_json", "target": "data_synonyms_\u65e0\u83cc", "relation": "contains", "confidence": "EXTRACTED", "source_file": "data/synonyms.json", "source_location": "L86", "weight": 1.0}, {"source": "home_cbx_projects_autobiology_data_synonyms_json", "target": "data_synonyms_sterile", "relation": "contains", "confidence": "EXTRACTED", "source_file": "data/synonyms.json", "source_location": "L87", "weight": 1.0}, {"source": "home_cbx_projects_autobiology_data_synonyms_json", "target": "data_synonyms_\u907f\u5149", "relation": "contains", "confidence": "EXTRACTED", "source_file": "data/synonyms.json", "source_location": "L88", "weight": 1.0}, {"source": "home_cbx_projects_autobiology_data_synonyms_json", "target": "data_synonyms_dark_condition", "relation": "contains", "confidence": "EXTRACTED", "source_file": "data/synonyms.json", "source_location": "L89", "weight": 1.0}, {"source": "home_cbx_projects_autobiology_data_synonyms_json", "target": "data_synonyms_co2", "relation": "contains", "confidence": "EXTRACTED", "source_file": "data/synonyms.json", "source_location": "L90", "weight": 1.0}, {"source": "home_cbx_projects_autobiology_data_synonyms_json", "target": "data_synonyms_co2", "relation": "contains", "confidence": "EXTRACTED", "source_file": "data/synonyms.json", "source_location": "L91", "weight": 1.0}, {"source": "home_cbx_projects_autobiology_data_synonyms_json", "target": "data_synonyms_\u4e8c\u6c27\u5316\u78b3", "relation": "contains", "confidence": "EXTRACTED", "source_file": "data/synonyms.json", "source_location": "L92", "weight": 1.0}]}